README.md
setup.py
convoys/__init__.py
convoys/autograd_scipy_monkeypatch.py
convoys/multi.py
convoys/plotting.py
convoys/regression.py
convoys/regression2.py
convoys/single.py
convoys/utils.py
convoys.egg-info/PKG-INFO
convoys.egg-info/SOURCES.txt
convoys.egg-info/dependency_links.txt
convoys.egg-info/requires.txt
convoys.egg-info/top_level.txt
examples/__init__.py
examples/dob_violations.py
examples/marriage.py