Metadata-Version: 1.0
Name: convoys
Version: 0.1.6
Summary: Fit machine learning models to predict conversion using Weibull and Gamma distributions
Home-page: https://better.engineering/convoys
Author: Erik Bernhardsson
Author-email: erikbern@better.com
License: MIT
Platform: UNKNOWN
